README.md
setup.py
japscandownloader/__init__.py
japscandownloader/jsd_selenium.py
japscandownloader/main.py
japscandownloader.egg-info/PKG-INFO
japscandownloader.egg-info/SOURCES.txt
japscandownloader.egg-info/dependency_links.txt
japscandownloader.egg-info/entry_points.txt
japscandownloader.egg-info/requires.txt
japscandownloader.egg-info/top_level.txt
japscandownloader/helpers/__init__.py
japscandownloader/helpers/helper_argument.py
japscandownloader/helpers/helper_browser.py
japscandownloader/helpers/helper_config.py
japscandownloader/helpers/helper_format.py
japscandownloader/tests/__init__.py
japscandownloader/tests/test_argument.py
japscandownloader/tests/test_config.py
japscandownloader/tests/test_download.py
japscandownloader/tests/test_format.py
japscandownloader/tests/test_scrambling.py
japscandownloader/tests/utils.py