Metadata-Version: 2.1
Name: japscandownloader
Version: 1.0.6
Summary: Script to download mangas from JapScan
Home-page: https://github.com/Harkame/JapScanDownloader
Author: Harkame
License: UNKNOWN
Platform: UNKNOWN
Classifier: Programming Language :: Python
Provides-Extra: dev
